pyqt_foldable_item_list_widget/__init__.py
pyqt_foldable_item_list_widget/foldableItemListWidget.py
pyqt_foldable_item_list_widget/foldableListWidgetItemWidget.py
pyqt_foldable_item_list_widget/ico/__init__.py
pyqt_foldable_item_list_widget/ico/down-arrow.svg
pyqt_foldable_item_list_widget/ico/up-arrow.svg
pyqt_foldable_item_list_widget-0.0.12.dist-info/LICENSE
pyqt_foldable_item_list_widget-0.0.12.dist-info/METADATA
pyqt_foldable_item_list_widget-0.0.12.dist-info/WHEEL
pyqt_foldable_item_list_widget-0.0.12.dist-info/top_level.txt
pyqt_foldable_item_list_widget-0.0.12.dist-info/RECORD
