Metadata-Version: 2.1
Name: pyqt-foldable-item-list-widget
Version: 0.0.12
Summary: PyQt QListWidget which itemWidget is foldable
Home-page: https://github.com/yjg30737/pyqt-foldable-item-list-widget.git
Author: Jung Gyu Yoon
Author-email: yjg30737@gmail.com
License: MIT
Platform: UNKNOWN
License-File: LICENSE
Requires-Dist: PyQt5 (>=5.8)
Requires-Dist: pyqt-svg-button (>=0.0.1)
